awssh/__init__.py
awssh/awssh.py
awssh/cli.py
jh_awssh-0.31.8.dist-info/AUTHORS.rst
jh_awssh-0.31.8.dist-info/LICENSE
jh_awssh-0.31.8.dist-info/METADATA
jh_awssh-0.31.8.dist-info/WHEEL
jh_awssh-0.31.8.dist-info/entry_points.txt
jh_awssh-0.31.8.dist-info/top_level.txt
jh_awssh-0.31.8.dist-info/RECORD
