Metadata-Version: 2.1
Name: jh-awssh
Version: 0.31.8
Summary: SSH Connect to Ec2 instances
Home-page: https://github.com/ibejohn818/awssh
Author: John Hardy
Author-email: john.hardy@me.com
License: MIT license
Keywords: awssh
Platform: UNKNOWN
Classifier: Intended Audience :: Developers
Classifier: License :: OSI Approved :: MIT License
Classifier: Natural Language :: English
Classifier: Programming Language :: Python :: 2.7
Classifier: Programming Language :: Python :: 3.5
Requires-Dist: Click
Requires-Dist: boto3
Requires-Dist: termcolor
Requires-Dist: jmespath
Requires-Dist: six
